tests/__init__.py
tests/test_trinnov_altitude.py
trinnov_altitude/__init__.py
trinnov_altitude/const.py
trinnov_altitude/exceptions.py
trinnov_altitude/messages.py
trinnov_altitude/mocks.py
trinnov_altitude/trinnov_altitude.py
trinnov_altitude-1.2.8.dist-info/licenses/LICENSE
trinnov_altitude-1.2.8.dist-info/METADATA
trinnov_altitude-1.2.8.dist-info/WHEEL
trinnov_altitude-1.2.8.dist-info/top_level.txt
trinnov_altitude-1.2.8.dist-info/RECORD
