Metadata-Version: 2.4
Name: trinnov-altitude
Version: 1.2.8
Summary: "Python client for interfacing with the Trinnov Altitude processor."
Home-page: https://github.com/binarylogic/py-trinnov-altitude
Author: Ben Johnson
Author-email: ben@binarylogic.com
License: Apache 2.0
Classifier: Intended Audience :: Developers
Classifier: Programming Language :: Python :: 3
Classifier: Programming Language :: Python :: 3.8
Classifier: Programming Language :: Python :: 3.9
Classifier: Programming Language :: Python :: 3.10
Classifier: Programming Language :: Python :: 3.11
Classifier: Programming Language :: Python :: 3.12
Classifier: License :: OSI Approved :: Apache Software License
Classifier: Operating System :: OS Independent
Classifier: Topic :: Software Development :: Libraries
Classifier: Topic :: Home Automation
Requires-Python: >=3.8
License-File: LICENSE
Requires-Dist: wakeonlan>=3.1
Dynamic: license-file
